{
    "Ar36": {
        "error": 0.00019066413789609225,
        "error_type": "",
        "fit": "previous",
        "references": [
            {
                "exclude": false,
                "record_id": "ba-01-A-17317"
            }
        ],
        "value": 0.006491531900950986
    },
    "Ar37": {
        "error": 0.009597713292395027,
        "error_type": "",
        "fit": "previous",
        "references": [
            {
                "exclude": false,
                "record_id": "ba-01-A-17317"
            }
        ],
        "value": -0.021512940271329693
    },
    "Ar38": {
        "error": 0.011913293913539097,
        "error_type": "",
        "fit": "previous",
        "references": [
            {
                "exclude": false,
                "record_id": "ba-01-A-17317"
            }
        ],
        "value": -0.000727504025963297
    },
    "Ar39": {
        "error": 0.009997970511125243,
        "error_type": "",
        "fit": "previous",
        "references": [
            {
                "exclude": false,
                "record_id": "ba-01-A-17317"
            }
        ],
        "value": 0.011263248125096135
    },
    "Ar40": {
        "error": 0.023400944828526248,
        "error_type": "",
        "fit": "previous",
        "references": [
            {
                "exclude": false,
                "record_id": "ba-01-A-17317"
            }
        ],
        "value": 1.9716908251845229
    }
}